{
  "PHI": {
    "ticket": 28,
    "money": 35
  },
  "PIT": {
    "ticket": 72,
    "money": 65
  },
  "BAL": {
    "ticket": 67,
    "money": 67
  },
  "WSH": {
    "ticket": 33,
    "money": 33
  },
  "TOR": {
    "ticket": 69,
    "money": 73
  },
  "DET": {
    "ticket": 31,
    "money": 27
  },
  "MIA": {
    "ticket": 22,
    "money": 36
  },
  "TB": {
    "ticket": 78,
    "money": 64
  },
  "CIN": {
    "ticket": 26,
    "money": 50
  },
  "CLE": {
    "ticket": 74,
    "money": 50
  },
  "MIL": {
    "ticket": 68,
    "money": 69
  },
  "MIN": {
    "ticket": 32,
    "money": 31
  },
  "NYY": {
    "ticket": 81,
    "money": 86
  },
  "NYM": {
    "ticket": 19,
    "money": 14
  },
  "CHC": {
    "ticket": 74,
    "money": 72
  },
  "CWS": {
    "ticket": 26,
    "money": 28
  },
  "TEX": {
    "ticket": 39,
    "money": 24
  },
  "HOU": {
    "ticket": 61,
    "money": 76
  },
  "KC": {
    "ticket": 44,
    "money": 53
  },
  "STL": {
    "ticket": 56,
    "money": 47
  },
  "ARI": {
    "ticket": 70,
    "money": 75
  },
  "COL": {
    "ticket": 30,
    "money": 25
  },
  "LAD": {
    "ticket": 85,
    "money": 56
  },
  "LAA": {
    "ticket": 15,
    "money": 44
  },
  "SD": {
    "ticket": 32,
    "money": 69
  },
  "SEA": {
    "ticket": 68,
    "money": 31
  },
  "SF": {
    "ticket": 24,
    "money": 22
  },
  "ATH": {
    "ticket": 76,
    "money": 78
  }
}