[
  {
    "home": "Chicago White Sox",
    "away": "Detroit Tigers",
    "temp": 66,
    "wind_speed": 15,
    "wind_deg": 60,
    "humidity": 48,
    "wind_dir": "In from Left",
    "status": "Green",
    "notes": "Winds blowing at 15mph, a bit in from left, a bit left to right."
  },
  {
    "home": "Washington Nationals",
    "away": "San Diego Padres",
    "temp": 71,
    "wind_speed": 16,
    "wind_deg": 360,
    "humidity": 37,
    "wind_dir": "In from Center",
    "status": "Green",
    "notes": "Winds blowing in at 10-15mph."
  },
  {
    "home": "Texas Rangers",
    "away": "Kansas City Royals",
    "temp": 92,
    "wind_speed": 11,
    "wind_deg": 190,
    "humidity": 38,
    "wind_dir": "Indoor",
    "status": "Roof",
    "notes": ""
  },
  {
    "home": "Pittsburgh Pirates",
    "away": "Minnesota Twins",
    "temp": 70,
    "wind_speed": 10,
    "wind_deg": 20,
    "humidity": 32,
    "wind_dir": "Out to Right",
    "status": "Green",
    "notes": "I think winds here are blowing mostly out to right, 10mph."
  },
  {
    "home": "Baltimore Orioles",
    "away": "Toronto Blue Jays",
    "temp": 72,
    "wind_speed": 16,
    "wind_deg": 350,
    "humidity": 35,
    "wind_dir": "In from Center",
    "status": "Green",
    "notes": "Winds blowing in at 10-15mph."
  },
  {
    "home": "Tampa Bay Rays",
    "away": "Los Angeles Angels",
    "temp": 85,
    "wind_speed": 10,
    "wind_deg": 270,
    "humidity": 72,
    "wind_dir": "Indoor",
    "status": "Roof",
    "notes": ""
  },
  {
    "home": "New York Mets",
    "away": "Miami Marlins",
    "temp": 61,
    "wind_speed": 18,
    "wind_deg": 10,
    "humidity": 46,
    "wind_dir": "In from Center",
    "status": "Green",
    "notes": "Winds blowing in at 15mph or more."
  },
  {
    "home": "Houston Astros",
    "away": "Milwaukee Brewers",
    "temp": 93,
    "wind_speed": 6,
    "wind_deg": 160,
    "humidity": 46,
    "wind_dir": "Indoor",
    "status": "Roof",
    "notes": ""
  },
  {
    "home": "Cleveland Guardians",
    "away": "Boston Red Sox",
    "temp": 69,
    "wind_speed": 14,
    "wind_deg": 40,
    "humidity": 39,
    "wind_dir": "In from Center",
    "status": "Green",
    "notes": "Winds blowing in at 10-15mph."
  },
  {
    "home": "St. Louis Cardinals",
    "away": "Chicago Cubs",
    "temp": 83,
    "wind_speed": 9,
    "wind_deg": 100,
    "humidity": 53,
    "wind_dir": "Out to Center",
    "status": "Yellow",
    "notes": "YELLOW - I expect we play a full game here, and the likely outcome is that we do it without any in-game issues, but... there's a few showers and storms around, especially early. A late start or an early delay is possible if one pops in the wrong spot."
  },
  {
    "home": "Cincinnati Reds",
    "away": "Atlanta Braves",
    "temp": 74,
    "wind_speed": 9,
    "wind_deg": 60,
    "humidity": 46,
    "wind_dir": "Cross",
    "status": "Neutral",
    "notes": ""
  },
  {
    "home": "Colorado Rockies",
    "away": "San Francisco Giants",
    "temp": 74,
    "wind_speed": 9,
    "wind_deg": 320,
    "humidity": 23,
    "wind_dir": "Out to Center",
    "status": "Neutral",
    "notes": ""
  },
  {
    "home": "Oakland Athletics",
    "away": "New York Yankees",
    "temp": 81,
    "wind_speed": 5,
    "wind_deg": 240,
    "humidity": 34,
    "wind_dir": "In from Center",
    "status": "Neutral",
    "notes": ""
  },
  {
    "home": "Seattle Mariners",
    "away": "Arizona Diamondbacks",
    "temp": 63,
    "wind_speed": 6,
    "wind_deg": 350,
    "humidity": 48,
    "wind_dir": "Indoor",
    "status": "Roof",
    "notes": ""
  },
  {
    "home": "Los Angeles Dodgers",
    "away": "Philadelphia Phillies",
    "temp": 69,
    "wind_speed": 9,
    "wind_deg": 230,
    "humidity": 61,
    "wind_dir": "In from Center",
    "status": "Neutral",
    "notes": ""
  }
]