[
    {
        "game_id": "50bf885c9e829f1de48161f3ec47e5dc",
        "team_away": "Minnesota Twins",
        "team_home": "Washington Nationals",
        "away_opening_ml": -136,
        "away_current_ml": -126,
        "home_opening_ml": 113,
        "home_current_ml": 105,
        "opening_total": 9.5,
        "current_total": 9.5,
        "commence_time": "2026-05-06T22:46:00Z"
    },
    {
        "game_id": "30d2a93f1ca79f37c19806e74ed1cdab",
        "team_away": "Cleveland Guardians",
        "team_home": "Kansas City Royals",
        "away_opening_ml": 109,
        "away_current_ml": 117,
        "home_opening_ml": -131,
        "home_current_ml": -141,
        "opening_total": 8.0,
        "current_total": 7.5,
        "commence_time": "2026-05-06T23:41:00Z"
    },
    {
        "game_id": "8379550b6a949466b56d6ddffad2b2fe",
        "team_away": "Athletics",
        "team_home": "Philadelphia Phillies",
        "away_opening_ml": 144,
        "away_current_ml": 139,
        "home_opening_ml": -175,
        "home_current_ml": -168,
        "opening_total": 8.5,
        "current_total": 8.0,
        "commence_time": "2026-05-06T22:41:00Z"
    },
    {
        "game_id": "3d9ff7b926b247cb73447ca5c7a7428e",
        "team_away": "New York Mets",
        "team_home": "Colorado Rockies",
        "away_opening_ml": -166,
        "away_current_ml": -156,
        "home_opening_ml": 140,
        "home_current_ml": 129,
        "opening_total": 10.0,
        "current_total": 9.5,
        "commence_time": "2026-05-07T01:21:00Z"
    },
    {
        "game_id": "4a14bd2383b640b8cf105c59c99fa882",
        "team_away": "Boston Red Sox",
        "team_home": "Detroit Tigers",
        "away_opening_ml": -102,
        "away_current_ml": -110,
        "home_opening_ml": -116,
        "home_current_ml": -110,
        "opening_total": 8.0,
        "current_total": 8.5,
        "commence_time": "2026-05-06T22:41:00Z"
    },
    {
        "game_id": "a524558d8c67f4e0116d63123b26e426",
        "team_away": "Cincinnati Reds",
        "team_home": "Chicago Cubs",
        "away_opening_ml": 144,
        "away_current_ml": 140,
        "home_opening_ml": -175,
        "home_current_ml": -169,
        "opening_total": 8.0,
        "current_total": 8.0,
        "commence_time": "2026-05-06T23:41:00Z"
    },
    {
        "game_id": "895be7e0cbc697eeffc1f4c9fb60613b",
        "team_away": "Texas Rangers",
        "team_home": "New York Yankees",
        "away_opening_ml": 159,
        "away_current_ml": 149,
        "home_opening_ml": -193,
        "home_current_ml": -181,
        "opening_total": 8.5,
        "current_total": 8.5,
        "commence_time": "2026-05-06T23:06:00Z"
    },
    {
        "game_id": "7dd3ac6bd80317fdd884080b8d94dd77",
        "team_away": "Baltimore Orioles",
        "team_home": "Miami Marlins",
        "away_opening_ml": 109,
        "away_current_ml": 109,
        "home_opening_ml": -131,
        "home_current_ml": -131,
        "opening_total": 8.5,
        "current_total": 8.5,
        "commence_time": "2026-05-06T22:41:00Z"
    },
    {
        "game_id": "de899b461227924fc52c2f9492e9fe56",
        "team_away": "Pittsburgh Pirates",
        "team_home": "Arizona Diamondbacks",
        "away_opening_ml": -156,
        "away_current_ml": -126,
        "home_opening_ml": 129,
        "home_current_ml": 104,
        "opening_total": 8.0,
        "current_total": 7.5,
        "commence_time": "2026-05-07T01:41:00Z"
    }
]